[
  {
    "file_content": "[\n  {\n    \"keyword\": \"bitcoin\",\n    \"graph_data\": [\n      {\n        \"title\": \"Texas Invests $5 Million in Bitcoin Under New Law - GovTech\",\n        \"url\": \"https://insider.govtech.com/texas/news/texas-invests-5-million-in-bitcoin-under-new-law\",\n        \"entities\": [\n          \"Texas\",\n          \"Digital Asset Reserve\",\n          \"BlackRock\",\n          \"Texas Blockchain Council\"\n        ],\n        \"score\": 73.59,\n        \"sentiment\": 1\n      },\n      {\n        \"title\": \"'Next Step Is Coming'—SEC Chair Issues 'Huge' Crypto Prediction As The Bitcoin Price Struggles - Forbes\",\n        \"url\": \"https://www.forbes.com/sites/digital-assets/2025/12/07/next-step-is-coming-sec-chair-issues-huge-crypto-prediction-as-the-bitcoin-price-struggles/\",\n        \"entities\": [\n          \"SEC\",\n          \"Tokenization\",\n          \"BlackRock\",\n          \"Blockchain\"\n        ],\n        \"score\": 71.45,\n        \"sentiment\": 0.5\n      },\n      {\n        \"title\": \"Sen. Gillibrand says 'nothing is holding up' progress on crypto market regulation: CNBC Crypto World - CNBC\",\n        \"url\": \"https://www.cnbc.com/video/2025/12/09/sen-gillibrand-says-nothing-is-holding-up-progress-on-crypto-market-regulation-cnbc-crypto-world.html\",\n        \"entities\": [\n          \"Senate Banking Committee\",\n          \"Cryptocurrency\",\n          \"Cynthia Lummis\",\n          \"Fed\"\n        ],\n        \"score\": 69.36,\n        \"sentiment\": 1\n      },\n      {\n        \"title\": \"ETFs in the Crossfire Amid Bitcoin’s Growing Self-Custody Debate - Yahoo Finance\",\n        \"url\": \"https://finance.yahoo.com/news/etfs-crossfire-amid-bitcoin-growing-215004125.html\",\n        \"entities\": [\n          \"Self-Custody\",\n          \"Exchanges\",\n          \"Institutional Rails\",\n          \"ETF\"\n        ],\n        \"score\": 69.06,\n        \"sentiment\": 0\n      },\n      {\n        \"title\": \"Crypto pros blast a potential move to exclude bitcoin holding companies from MSCI indexes - Business Insider\",\n        \"url\": \"https://www.businessinsider.com/msci-crypto-index-bitcoin-treasury-strategy-btc-price-2025-12\",\n        \"entities\": [\n          \"Investment Funds\",\n          \"Digital Assets\",\n          \"MSCI\",\n          \"Institutional Investors\"\n        ],\n        \"score\": 68.25,\n        \"sentiment\": -0.5\n      },\n      {\n        \"title\": \"Hyperscale Data Bitcoin Treasury at Approximately $75 Million – Company Announcement - Financial Times\",\n        \"url\": \"https://markets.ft.com/data/announce/detail?dockey=600-202512090600PR_NEWS_USPRX____SF42143-1\",\n        \"entities\": [\n          \"Sentinum\",\n          \"Open-Market Purchases\",\n          \"AI Data Centers\",\n          \"Digital Asset Treasury\"\n        ],\n        \"score\": 67,\n        \"sentiment\": 1\n      },\n      {\n        \"title\": \"Blockchain: Built to catch criminals - Thomson Reuters\",\n        \"url\": \"https://www.thomsonreuters.com/en-us/posts/corporates/blockchain-catch-criminals/\",\n        \"entities\": [\n          \"Blockchain\",\n          \"Crypto Forensics\",\n          \"Financial Crimes\",\n          \"Law Enforcement\"\n        ],\n        \"score\": 66.14,\n        \"sentiment\": 0.5\n      },\n      {\n        \"title\": \"Forget Interest Rates—Traders Are Quietly Braced For A $6.5 Trillion Fed Surprise That Could Blow Up Stocks, Crypto And The Bitcoin Price - Forbes\",\n        \"url\": \"https://www.forbes.com/sites/digital-assets/2025/12/09/forget-interest-rates-traders-are-quietly-bracing-for-65-trillion-fed-surprise-that-could-blow-up-stocks-crypto-and-the-bitcoin-price/\",\n        \"entities\": [\n          \"Cryptocurrency\",\n          \"BlackRock\",\n          \"Fed\",\n          \"Market Sentiment\"\n        ],\n        \"score\": 65.56,\n        \"sentiment\": -0.5\n      },\n      {\n        \"title\": \"Bitcoin's 2025 rollercoaster may end on a low - Reuters\",\n        \"url\": \"https://www.reuters.com/business/finance/bitcoins-2025-rollercoaster-may-end-low-2025-12-09/\",\n        \"entities\": [\n          \"Institutional Investors\",\n          \"Stock Market Sentiment\",\n          \"AI Stocks\",\n          \"Derivatives\"\n        ],\n        \"score\": 64.16,\n        \"sentiment\": -0.5\n      },\n      {\n        \"title\": \"Everything Everywhere All At Once – Now Tokenized - Forbes\",\n        \"url\": \"https://www.forbes.com/sites/fredhubler/2025/12/09/everything-everywhere-all-at-once--now-tokenized/\",\n        \"entities\": [\n          \"Tokenized RWAs\",\n          \"Fine Art\",\n          \"Real Estate\",\n          \"Blockchain\",\n          \"Private Credit\"\n        ],\n        \"score\": 63.97,\n        \"sentiment\": 0.5\n      },\n      {\n        \"title\": \"There's no Dow or S&P 500 for cryptocurrencies yet. Bitwise is getting a step closer with new ETF - CNBC\",\n        \"url\": \"https://www.cnbc.com/2025/12/09/theres-no-dow-or-sp-500-for-cryptocurrencies-yet-bitwise-is-getting-a-step-closer-with-new-etf.html\",\n        \"entities\": [\n          \"XRP\",\n          \"Bitwise 10 Crypto Index ETF\",\n          \"Solana\",\n          \"Avalanche\"\n        ],\n        \"score\": 61.8,\n        \"sentiment\": 0\n      },\n      {\n        \"title\": \"Crypto fortunes vanishing: Estate planning crisis hits digital wealth - The Tech Buzz\",\n        \"url\": \"https://www.techbuzz.ai/articles/crypto-fortunes-vanishing-estate-planning-crisis-hits-digital-wealth\",\n        \"entities\": [\n          \"Estate Tax\",\n          \"Estate Planning\",\n          \"Cryptocurrency\",\n          \"Digital Wealth\"\n        ],\n        \"score\": 56.65,\n        \"sentiment\": -0.5\n      },\n      {\n        \"title\": \"BlackRock files application with SEC for staked ether ETF: CNBC Crypto World - CNBC\",\n        \"url\": \"https://www.cnbc.com/video/2025/12/08/blackrock-files-application-with-sec-for-staked-ether-etf-cnbc-crypto-world.html\",\n        \"entities\": [\n          \"SEC\",\n          \"Ether\",\n          \"BlackRock\",\n          \"Ondo Finance\"\n        ],\n        \"score\": 54.75,\n        \"sentiment\": 0\n      },\n      {\n        \"title\": \"Falling crypto prices put investors in a 'unique' position to take advantage of a classic tax strategy, says CPA - CNBC\",\n        \"url\": \"https://www.cnbc.com/2025/12/03/cpa-falling-crypto-prices-put-investors-in-position-for-tax-loss-harvesting.html\",\n        \"entities\": [\n          \"Short-Term Capital Gains\",\n          \"Crypto Investments\",\n          \"Tax Loss Harvesting\",\n          \"Marianela Collado\",\n          \"IRS\"\n        ],\n        \"score\": 54.28,\n        \"sentiment\": 0.5\n      },\n      {\n        \"title\": \"Is an ETF Safer than an Exchange for Bitcoin? - BeInCrypto\",\n        \"url\": \"https://beincrypto.com/etfs-crossfire-bitcoin-self-custody-debate/\",\n        \"entities\": [\n          \"Self-Custody\",\n          \"Custodial Trust\",\n          \"ETF\",\n          \"Institutional Influence\"\n        ],\n        \"score\": 53.93,\n        \"sentiment\": 0\n      },\n      {\n        \"title\": \"Should You Buy Bitcoin While It's Under $100,000? - The Motley Fool\",\n        \"url\": \"https://www.fool.com/investing/2025/12/05/should-you-buy-bitcoin-while-its-under-100000/\",\n        \"entities\": [\n          \"Bull Market\",\n          \"Cryptocurrency\",\n          \"Debt\",\n          \"MicroStrategy\"\n        ],\n        \"score\": 53.15,\n        \"sentiment\": 0.5\n      },\n      {\n        \"title\": \"CNBC: Biggest Crypto Estate Planning and Tax Mistakes Investors Make in 2025 - Blockchain News\",\n        \"url\": \"https://blockchain.news/flashnews/biggest-crypto-estate-planning-and-tax-mistakes-investors-make-in-2025\",\n        \"entities\": [\n          \"Digital Assets\",\n          \"Estate Planning\",\n          \"Crypto Investors\",\n          \"Ethereum\"\n        ],\n        \"score\": 48.64,\n        \"sentiment\": 0\n      },\n      {\n        \"title\": \"American Bitcoin increases holdings by 363 bitcoins, bringing total holdings to 4,367 bitcoins - Bitget\",\n        \"url\": \"https://www.bitget.com/amp/news/detail/12560605095940\",\n        \"entities\": [\n          \"American Bitcoin\",\n          \"Cryptocurrency\",\n          \"Trump Family\",\n          \"Crypto Mining\"\n        ],\n        \"score\": 44.33,\n        \"sentiment\": 0\n      }\n    ],\n    \"node_count\": 18\n  },\n  {\n    \"keyword\": \"rare earth\",\n    \"graph_data\": [\n      {\n        \"title\": \"Liontown inks spodumene supply deal with China’s Canmax Technologies - Mining.com\",\n        \"url\": \"https://www.mining.com/web/liontown-inks-spodumene-supply-deal-with-chinas-canmax-technologies/\",\n        \"entities\": [\n          \"China\",\n          \"Spodumene\",\n          \"Canmax Technologies\",\n          \"Lithium Demand\",\n          \"Liontown\"\n        ],\n        \"score\": 79.83,\n        \"sentiment\": 1\n      },\n      {\n        \"title\": \"US military developing small refineries for critical minerals - Reuters\",\n        \"url\": \"https://www.reuters.com/business/energy/us-military-developing-small-refineries-critical-minerals-2025-12-09/\",\n        \"entities\": [\n          \"Critical Minerals\",\n          \"Antimony\",\n          \"U.S. Military\",\n          \"Rare Earths\",\n          \"Tungsten\"\n        ],\n        \"score\": 78.83,\n        \"sentiment\": 0.5\n      },\n      {\n        \"title\": \"Tronox stock jumps on $600M potential EXIM-EFA financing - Mining.com\",\n        \"url\": \"https://www.mining.com/tronox-stock-jumps-on-600m-potential-exim-efa-financing/\",\n        \"entities\": [\n          \"EXIM\",\n          \"titanium products\",\n          \"EFA\",\n          \"Tronox\"\n        ],\n        \"score\": 78.57,\n        \"sentiment\": 1\n      },\n      {\n        \"title\": \"ASM ‘deepens’ Noveon link as it looks to develop US operations - Australian Mining\",\n        \"url\": \"https://www.australianmining.com.au/asm-deepens-noveon-link-as-it-looks-to-develop-us-operations/\",\n        \"entities\": [\n          \"Sovereign Supply Chains\",\n          \"Electric Vehicles\",\n          \"Australian Strategic Materials\",\n          \"Noveon Magnetics\",\n          \"Neodymium Iron Boron Alloy\"\n        ],\n        \"score\": 77.88,\n        \"sentiment\": 0.7\n      },\n      {\n        \"title\": \"REalloys reaches rare earths tie-up with Canada-backed council - Mining.com\",\n        \"url\": \"https://www.mining.com/web/realloys-reaches-rare-earths-tie-up-with-canada-backed-council/\",\n        \"entities\": [\n          \"Canada-backed Council\",\n          \"Terbium Oxide\",\n          \"Dysprosium Oxide\",\n          \"Neodymium\",\n          \"Praseodymium\"\n        ],\n        \"score\": 74.74,\n        \"sentiment\": 1\n      },\n      {\n        \"title\": \"Morgan Stanley upgrades rare earth stock, says the U.S. has chosen it as solution to China's dominance - CNBC\",\n        \"url\": \"https://www.cnbc.com/2025/12/05/morgan-stanley-upgrades-rare-earth-stock-says-the-us-has-chosen-it-as-solution-to-chinas-dominance.html\",\n        \"entities\": [\n          \"MP Materials\",\n          \"China\",\n          \"U.S. Supply Chains\",\n          \"Rare Earth Stocks\",\n          \"Morgan Stanley\"\n        ],\n        \"score\": 71.45,\n        \"sentiment\": 1\n      },\n      {\n        \"title\": \"Tasmania emerges as rare earths hub - Australian Mining\",\n        \"url\": \"https://www.australianmining.com.au/tasmania-emerges-as-rare-earths-hub/\",\n        \"entities\": [\n          \"Australian Nuclear Science and Technology Organisation\",\n          \"Mark Cooksey\",\n          \"Rare Earth Carbonate\",\n          \"ABx Group\",\n          \"Deep Leads Project\"\n        ],\n        \"score\": 71.34,\n        \"sentiment\": 1\n      },\n      {\n        \"title\": \"Greenland grants 30-year licence to EU-backed graphite project - Mining.com\",\n        \"url\": \"https://www.mining.com/greenland-grants-30-year-licence-to-eu-backed-graphite-project/\",\n        \"entities\": [\n          \"Long-term License\",\n          \"Mining Sector\",\n          \"Supply Stability\",\n          \"EU-backed Project\",\n          \"Greenland\",\n          \"Graphite\"\n        ],\n        \"score\": 70.94,\n        \"sentiment\": 0.5\n      },\n      {\n        \"title\": \"India’s journey to self-sustenance in the Rare Earth ecosystem - Times of India\",\n        \"url\": \"https://timesofindia.indiatimes.com/auto/news/indias-journey-to-self-sustenance-in-the-rare-earth-ecosystem/articleshow/125733951.cms\",\n        \"entities\": [\n          \"China\",\n          \"EV Market\",\n          \"Rare Earths\",\n          \"Indian Manufacturers\",\n          \"Neodymium\"\n        ],\n        \"score\": 69.69,\n        \"sentiment\": 0.5\n      },\n      {\n        \"title\": \"USA Rare Earth Subsidiary LCM Partners with Arnold Magnetic Technologies to Secure Rare Earth Metals Supply - The Manila Times\",\n        \"url\": \"https://www.manilatimes.net/2025/12/04/tmt-newswire/globenewswire/usa-rare-earth-subsidiary-lcm-partners-with-arnold-magnetic-technologies-to-secure-rare-earth-metals-supply/2236997\",\n        \"entities\": [\n          \"NdFeB Magnets\",\n          \"Rare Earth Metals\",\n          \"Arnold Magnetic Technologies\",\n          \"USA Rare Earth\",\n          \"Oklahoma\"\n        ],\n        \"score\": 69.21,\n        \"sentiment\": 1\n      },\n      {\n        \"title\": \"Morningstar starts coverage on Australia's Lynas, sees shares overpriced - TradingView\",\n        \"url\": \"https://www.tradingview.com/news/reuters.com,2025:newsml_L6N3XD04V:0-morningstar-starts-coverage-on-australia-s-lynas-sees-shares-overpriced/\",\n        \"entities\": [\n          \"Lynas\",\n          \"Neodymium-Praseodymium\",\n          \"Morningstar\",\n          \"Rare Earths\",\n          \"EVs\"\n        ],\n        \"score\": 68.04,\n        \"sentiment\": -0.5\n      },\n      {\n        \"title\": \"China to limit access to Nvidia's H200 chips despite Trump export approval, FT reports - Reuters\",\n        \"url\": \"https://www.reuters.com/world/china/nvidia-shares-gain-trump-allows-some-ai-chip-sales-china-2025-12-09/\",\n        \"entities\": [\n          \"China\",\n          \"AI Stocks\",\n          \"Semiconductors\",\n          \"Nvidia\",\n          \"H200 Chips\",\n          \"Trump\"\n        ],\n        \"score\": 67.79,\n        \"sentiment\": 0\n      },\n      {\n        \"title\": \"Johann Wadephul - Mining.com\",\n        \"url\": \"https://www.mining.com/web/germanys-top-diplomat-sees-progress-in-china-rare-earth-talks/54514436695_40b36ef08e_b/\",\n        \"entities\": [\n          \"Heavy Rare Earths\",\n          \"Mining Sector\",\n          \"Canada\",\n          \"REalloys\",\n          \"Production Capacity\"\n        ],\n        \"score\": 67.54,\n        \"sentiment\": 0\n      },\n      {\n        \"title\": \"US minerals projects seek ‘industrial vision’ from Washington to compete with China - KITCO\",\n        \"url\": \"https://www.kitco.com/news/off-the-wire/2025-12-05/us-minerals-projects-seek-industrial-vision-washington-compete-china\",\n        \"entities\": [\n          \"Nickel\",\n          \"US Export-Import Bank\",\n          \"Melissa Sanderson\",\n          \"Rare Earths\",\n          \"Perpetua Resources\"\n        ],\n        \"score\": 64.52,\n        \"sentiment\": 0.5\n      },\n      {\n        \"title\": \"The Failed Crusade to Keep a Rare-Earths Mine Out of China’s Hands - tovima.com\",\n        \"url\": \"https://www.tovima.com/wsj/the-failed-crusade-to-keep-a-rare-earths-mine-out-of-chinas-hands/\",\n        \"entities\": [\n          \"Peak\",\n          \"Appian Capital Advisory\",\n          \"Shenghe Resources\",\n          \"Rare Earths\",\n          \"Tanzania\"\n        ],\n        \"score\": 63.64,\n        \"sentiment\": -0.5\n      },\n      {\n        \"title\": \"Congo miners urge urgent talks to clear cobalt export backlog - KITCO\",\n        \"url\": \"https://www.kitco.com/news/off-the-wire/2025-12-08/congo-miners-urge-urgent-talks-clear-cobalt-export-backlog\",\n        \"entities\": [\n          \"China\",\n          \"Compliance Hurdles\",\n          \"EV Market\",\n          \"Battery Supply Chains\",\n          \"Cobalt\"\n        ],\n        \"score\": 62.29,\n        \"sentiment\": -0.5\n      },\n      {\n        \"title\": \"State seeks public input on Oregon’s first cyanide-processed gold mining operation\",\n        \"url\": \"https://oregoncapitalchronicle.com/2025/12/09/state-seeks-public-input-on-oregons-first-cyanide-processed-gold-mining-operation/\",\n        \"entities\": [\n          \"Sierra Club\",\n          \"Grassy Mountain Mine\",\n          \"Gold\",\n          \"Cyanide\",\n          \"Northern Paiute\"\n        ],\n        \"score\": 61.45,\n        \"sentiment\": -0.5\n      },\n      {\n        \"title\": \"MP Materials CEO Litinsky sells $24.2 million in stock By Investing.com - Investing.com Canada\",\n        \"url\": \"https://ca.investing.com/news/insider-trading-news/mp-materials-ceo-litinsky-sells-242-million-in-stock-93CH-4352311\",\n        \"entities\": [\n          \"MP Materials\",\n          \"rare earth supply chain\",\n          \"James Henry Litinsky\",\n          \"Morgan Stanley\",\n          \"BMO Capital\"\n        ],\n        \"score\": 60.84,\n        \"sentiment\": 0.5\n      },\n      {\n        \"title\": \"China Trade Surplus Tops $1 Trillion On Non-US Growth - Marine Link\",\n        \"url\": \"https://www.marinelink.com/news/china-trade-surplus-tops-trillion-nonus-533254\",\n        \"entities\": [\n          \"China\",\n          \"Southeast Asia\",\n          \"European Union\",\n          \"Trade Surplus\",\n          \"Tariffs\"\n        ],\n        \"score\": 56.82,\n        \"sentiment\": 0\n      },\n      {\n        \"title\": \"Lode Gold Enters into Exclusive LOI with a Mining Company to Advance Fremont Gold Project and Repay Debt - Yahoo Finance\",\n        \"url\": \"https://finance.yahoo.com/news/lode-gold-enters-exclusive-loi-210100584.html\",\n        \"entities\": [\n          \"Exploration Plans\",\n          \"Fremont Gold Project\",\n          \"Gold\",\n          \"Mining Company\",\n          \"Lode Gold\"\n        ],\n        \"score\": 51.36,\n        \"sentiment\": 0.5\n      },\n      {\n        \"title\": \"minerals-and-metals-to average-higher - Mining.com\",\n        \"url\": \"https://www.mining.com/global-scramble-for-critical-minerals-to-shape-markets-in-2026-bmi/minerals-and-metals-to-average-higher/\",\n        \"entities\": [\n          \"Brazil Mine\",\n          \"Mining Sector\",\n          \"BHP\",\n          \"Cash-Flowing Assets\",\n          \"Gold Royalty\"\n        ],\n        \"score\": 48.29,\n        \"sentiment\": 0\n      }\n    ],\n    \"node_count\": 21\n  },\n  {\n    \"keyword\": \"tesla\",\n    \"graph_data\": [\n      {\n        \"title\": \"Musk says new Tesla software allows texting and driving, which is illegal in most states - TechCrunch\",\n        \"url\": \"https://techcrunch.com/2025/12/04/musk-says-new-tesla-software-allows-texting-and-driving-which-is-illegal-in-most-states/\",\n        \"entities\": [\n          \"Full Self-Driving\",\n          \"Driver Assistance Software\",\n          \"California DMV\",\n          \"Elon Musk\"\n        ],\n        \"score\": 70.16,\n        \"sentiment\": -0.5\n      },\n      {\n        \"title\": \"Tesla launches low-cost Model 3 Standard in Europe in bid to recover market share - Automotive News\",\n        \"url\": \"https://www.autonews.com/tesla/ane-tesla-model-3-standard-europe-1204/\",\n        \"entities\": [\n          \"Electric Vehicles\",\n          \"European Market\",\n          \"Model 3\",\n          \"Market Share\"\n        ],\n        \"score\": 69.25,\n        \"sentiment\": 1\n      },\n      {\n        \"title\": \"2026 Tesla Model Y review: Spending one week with the new Model Y - Forbes\",\n        \"url\": \"https://www.forbes.com/sites/matthewmacconnell/2025/12/08/test-driving-the-2026-tesla-model-y/\",\n        \"entities\": [\n          \"Electric Vehicles\",\n          \"Auto Industry\",\n          \"Consumer Technology\",\n          \"Tesla Model Y\"\n        ],\n        \"score\": 69.21,\n        \"sentiment\": 0.5\n      },\n      {\n        \"title\": \"Trump plans to weaken vehicle mileage rules that limit air pollution - Los Angeles Times\",\n        \"url\": \"https://www.latimes.com/environment/story/2025-12-03/trump-plans-to-weaken-vehicle-mileage-rules-that-limit-air-pollution\",\n        \"entities\": [\n          \"Electric Vehicles\",\n          \"Auto Industry\",\n          \"Environmental Regulations\",\n          \"Trump Administration\"\n        ],\n        \"score\": 69.07,\n        \"sentiment\": -1\n      },\n      {\n        \"title\": \"Fuel economy rollback - Boise State Public Radio\",\n        \"url\": \"https://www.boisestatepublicradio.org/2025-12-03/fuel-economy-rollback\",\n        \"entities\": [\n          \"Automotive Sector\",\n          \"CAFE Standards\",\n          \"Electric Vehicles\",\n          \"Trump Administration\",\n          \"California Regulations\"\n        ],\n        \"score\": 68.33,\n        \"sentiment\": -0.5\n      },\n      {\n        \"title\": \"Tesla Makes Top 10 In ‘Consumer Reports’ 2026 Automotive Brand Ranking - Forbes\",\n        \"url\": \"https://www.forbes.com/sites/sashalekach/2025/12/04/tesla-makes-top-10-in-consumer-reports-2026-automotive-brand-ranking/\",\n        \"entities\": [\n          \"Consumer Reports\",\n          \"Rivian\",\n          \"Kia\",\n          \"Model Y\"\n        ],\n        \"score\": 67.19,\n        \"sentiment\": 1\n      },\n      {\n        \"title\": \"Trump administration rolls back fuel economy standards - Iowa Public Radio\",\n        \"url\": \"https://www.iowapublicradio.org/news-from-npr/2025-12-03/trump-administration-rolls-back-fuel-economy-standards\",\n        \"entities\": [\n          \"Electric Vehicles\",\n          \"Automotive Industry\",\n          \"California Air Resources Board\",\n          \"Fuel Economy Standards\"\n        ],\n        \"score\": 63.98,\n        \"sentiment\": -0.5\n      },\n      {\n        \"title\": \"Tesla Stock Today (TSLA): What to Know Before the Market Opens on December 8, 2025 - ts2.tech\",\n        \"url\": \"https://ts2.tech/en/tesla-stock-today-tsla-what-to-know-before-the-market-opens-on-december-8-2025/\",\n        \"entities\": [\n          \"Full Self-Driving\",\n          \"Cybertruck\",\n          \"European Demand\",\n          \"Elon Musk\"\n        ],\n        \"score\": 63.76,\n        \"sentiment\": -0.5\n      },\n      {\n        \"title\": \"Tesla Cracks Consumer Reports Top 10 For First Time As Aging Lineup Boosts Reliability - evxl.co\",\n        \"url\": \"https://evxl.co/2025/12/07/tesla-cracks-consumer-reports-top-10/\",\n        \"entities\": [\n          \"Electric Vehicles\",\n          \"Consumer Reports\",\n          \"Cybertruck\",\n          \"BYD\"\n        ],\n        \"score\": 54.53,\n        \"sentiment\": 0.5\n      },\n      {\n        \"title\": \"Here are Tuesday's biggest analyst calls: Nvidia, Apple, Tesla, Micron, Viking, Netflix, Apple, Viking, Delta & more - CNBC\",\n        \"url\": \"https://www.cnbc.com/2025/12/09/tuesday-stocks-from-analyst-calls-like-nvidia.html\",\n        \"entities\": [\n          \"Netflix\",\n          \"Apple\",\n          \"Nvidia\",\n          \"Micron\",\n          \"Delta\",\n          \"GM\"\n        ],\n        \"score\": 50.26,\n        \"sentiment\": 0\n      },\n      {\n        \"title\": \"Comparing pedestrian safety between electric and internal combustion engine vehicles - Nature\",\n        \"url\": \"https://www.nature.com/articles/s41467-025-66463-8\",\n        \"entities\": [\n          \"Electric Vehicles\",\n          \"Casualty Rates\",\n          \"Internal Combustion Engine Vehicles\",\n          \"Collision Avoidance Systems\",\n          \"Automotive Safety\"\n        ],\n        \"score\": 49.19,\n        \"sentiment\": 0\n      },\n      {\n        \"title\": \"Nokia and du show off some autonomous network slicing - Telecoms\",\n        \"url\": \"https://www.telecoms.com/5g-6g/nokia-and-du-show-off-some-autonomous-network-slicing\",\n        \"entities\": [\n          \"Nokia\",\n          \"du\",\n          \"Artificial Intelligence\",\n          \"Telecommunications\",\n          \"5G Technology\"\n        ],\n        \"score\": 42.15,\n        \"sentiment\": 0.5\n      },\n      {\n        \"title\": \"Fed Meeting: Job Openings Jump, But Don't Worry About Hawkish Shift - Investor's Business Daily\",\n        \"url\": \"https://www.investors.com/news/economy/federal-reserve-meeting-dec-rate-cut-projections-sp-500/\",\n        \"entities\": [\n          \"Job Openings\",\n          \"Equities\",\n          \"Nvidia\",\n          \"Interest Rates\",\n          \"Fed Rates\"\n        ],\n        \"score\": 41.16,\n        \"sentiment\": 0\n      }\n    ],\n    \"node_count\": 13\n  }\n]",
    "file_name": "graph_data_2025-12-10.json"
  }
]
